imdbmovies/__init__.py
imdbmovies/imdb.py
imdbmovies/parser.py
imdbmovies-0.1.1.dist-info/LICENSE
imdbmovies-0.1.1.dist-info/METADATA
imdbmovies-0.1.1.dist-info/WHEEL
imdbmovies-0.1.1.dist-info/top_level.txt
imdbmovies-0.1.1.dist-info/RECORD
