Metadata-Version: 2.1
Name: imdbmovies
Version: 0.1.1
Summary: IMDB API for Python
Home-page: https://github.com/safevideo/imdbmovies
Author: safevideo
License-File: LICENSE
Requires-Dist: beautifulsoup4
